[
  {
    "id": "1232071069268049920",
    "url": "https://cdn.discordapp.com/avatar-decoration-presets/a_a47890109a231f72dae7b17b27164676.png?size=240&passthrough=true",
    "label": "A glittering ring of colorful stardust adorns the avatar with a celestial touch.",
    "category": "decorations",
    "emoji": "<emoji_1232071069268049920:1238864757491109889>"
  },
  {
    "id": "1232071159860822117",
    "url": "https://cdn.discordapp.com/avatar-decoration-presets/a_6d16b27d9415cafe3b289053644337c4.png?size=240&passthrough=true",
    "label": "A mesmerizing dark hole swirls around the avatar",
    "category": "decorations",
    "emoji": "<emoji_1232071159860822117:1238864793276907634>"
  },
  {
    "id": "1232071714909847682",
    "url": "https://cdn.discordapp.com/avatar-decoration-presets/a_8552f9857793aed0cf816f370e2df3be.png?size=240&passthrough=true",
    "label": "Star constellations decorate the avatar",
    "category": "decorations",
    "emoji": "<emoji_1232071714909847682:1238864813485199450>"
  },
  {
    "id": "1232072123950956635",
    "url": "https://cdn.discordapp.com/avatar-decoration-presets/a_9a6bf0ab30a6719d6eb09fa4996984ca.png?size=240&passthrough=true",
    "label": "Three planets orbit around an avatar engulfed by solar flames.",
    "category": "decorations",
    "emoji": "<emoji_1232072123950956635:1238864840840188026>"
  },
  {
    "id": "1232072522690854964",
    "url": "https://cdn.discordapp.com/avatar-decoration-presets/a_6fdbddb6229453eac3bbb212edf5cd1c.png?size=240&passthrough=true",
    "label": "A UFO appears and emits an abduction beam before flying away... talk about a grab-and-go.",
    "category": "decorations",
    "emoji": "<emoji_1232072522690854964:1238864850667438171>"
  },
  {
    "id": "1232072861636755466",
    "url": "https://cdn.discordapp.com/avatar-decoration-presets/a_c9b84ee80a335a9d59b69352e34574f6.png?size=240&passthrough=true",
    "label": "The avatar wears an astronaut helmet. Protecting your head is always a good look.",
    "category": "decorations",
    "emoji": "<emoji_1232072861636755466:1238864880334016644>"
  },
  {
    "id": "1228246415449264168",
    "url": "https://cdn.discordapp.com/avatar-decoration-presets/a_49c479e15533fb4c02eb320c9c137433.png?size=240&passthrough=true",
    "label": "Waves of color pulsate around the avatar to the tempo of lo-fi hip hop beats.",
    "category": "decorations",
    "emoji": "<emoji_1228246415449264168:1238864901699539017>"
  },
  {
    "id": "1228251189276184618",
    "url": "https://cdn.discordapp.com/avatar-decoration-presets/a_77b7b6a740a9451e1ef39c0252154ef8.png?size=240&passthrough=true",
    "label": "An adorable cat sleeps peacefully on the avatar.",
    "category": "decorations",
    "emoji": "<emoji_1228251189276184618:1238864911187050497>"
  },
  {
    "id": "1228251373158793251",
    "url": "https://cdn.discordapp.com/avatar-decoration-presets/a_f740031cc97d1b7eb73c0d0ac1dd09f3.png?size=240&passthrough=true",
    "label": "Stringlights and a lovely houseplant adorn the frame of the avatar for the ultimate cozy mood.",
    "category": "decorations",
    "emoji": "<emoji_1228251373158793251:1238864924629930007>"
  },
  {
    "id": "1228251862709567508",
    "url": "https://cdn.discordapp.com/avatar-decoration-presets/a_e8c11f139e55dac538cdaafb3caa2317.png?size=240&passthrough=true",
    "label": "Raindrops sprinkle outside of the avatar through a window's view for a calming ambiance.",
    "category": "decorations",
    "emoji": "<emoji_1228251862709567508:1238864950978416680>"
  },
  {
    "id": "1228252061171449876",
    "url": "https://cdn.discordapp.com/avatar-decoration-presets/a_bb71042ccd2ca277a69f086a4f3354d0.png?size=240&passthrough=true",
    "label": "An avatar wearing a pair of stylish headphones.",
    "category": "decorations",
    "emoji": "<emoji_1228252061171449876:1238864965205753939>"
  },
  {
    "id": "1228252237407588382",
    "url": "https://cdn.discordapp.com/avatar-decoration-presets/a_5873ecaa76fb549654b40095293f902e.png?size=240&passthrough=true",
    "label": "A pen scribbles a cheeky smiley face on a small notebook next to a pair of earbuds.",
    "category": "decorations",
    "emoji": "<emoji_1228252237407588382:1238864979071864884>"
  },
  {
    "id": "1220513979898793994",
    "url": "https://cdn.discordapp.com/avatar-decoration-presets/a_98555e40cc6802bd3a4fed906af1d992.png?size=240&passthrough=true",
    "label": "Clove's special smoke ability wraps around the avatar",
    "category": "decorations",
    "emoji": "<emoji_1220513979898793994:1238865006284636351>"
  },
  {
    "id": "1220513986051837952",
    "url": "https://cdn.discordapp.com/avatar-decoration-presets/a_c45abe8c7585fdb41b8d8d4d666f1588.png?size=240&passthrough=true",
    "label": "The avatar wears Omen's signature hood.",
    "category": "decorations",
    "emoji": "<emoji_1220513986051837952:1238865034726080582>"
  },
  {
    "id": "1220513991449907280",
    "url": "https://cdn.discordapp.com/avatar-decoration-presets/a_a87e3efa4de2956331831681231ce63b.png?size=240&passthrough=true",
    "label": "Reyna's Leer ability surrounds the avatar",
    "category": "decorations",
    "emoji": "<emoji_1220513991449907280:1238865069555585056>"
  },
  {
    "id": "1220513996889919548",
    "url": "https://cdn.discordapp.com/avatar-decoration-presets/a_09de63526a45be1ddac70e84718ee04a.png?size=240&passthrough=true",
    "label": "A kill icon displaying 5 confirmed kills.",
    "category": "decorations",
    "emoji": "<emoji_1220513996889919548:1238865087792414855>"
  },
  {
    "id": "1220514050551709787",
    "url": "https://cdn.discordapp.com/avatar-decoration-presets/a_904b1989077c91fca1168d39bfcaa0a4.png?size=240&passthrough=true",
    "label": "The avatar equips throwing knives from Jett's signature Blade Storm ability.",
    "category": "decorations",
    "emoji": "<emoji_1220514050551709787:1238865107908431912>"
  },
  {
    "id": "1217624823656611952",
    "url": "https://cdn.discordapp.com/avatar-decoration-presets/a_27bbf0b53b1054cf61e9a4c0e8d4027f.png?size=240&passthrough=true",
    "label": "A jubilant bee buzzes around an avatar adorned with lush petals. We must protect them at all costs.",
    "category": "decorations",
    "emoji": "<emoji_1217624823656611952:1238865123657912442>"
  },
  {
    "id": "1217625430320742551",
    "url": "https://cdn.discordapp.com/avatar-decoration-presets/a_629689577fa1da2ef0061a5a8c930de1.png?size=240&passthrough=true",
    "label": "A pair of fluffy dandelions have their florets dispersed by a gentle breeze.",
    "category": "decorations",
    "emoji": "<emoji_1217625430320742551:1238865137964683314>"
  },
  {
    "id": "1217625725092233236",
    "url": "https://cdn.discordapp.com/avatar-decoration-presets/a_0c0eeb351ae2cf48c6e1eee2cae49d40.png?size=240&passthrough=true",
    "label": "A living rainbow suddently loses its colorful hues and unleashes a stormy lament.",
    "category": "decorations",
    "emoji": "<emoji_1217625725092233236:1238865148974858292>"
  },
  {
    "id": "1217625936015392890",
    "url": "https://cdn.discordapp.com/avatar-decoration-presets/a_9867b1ba56601e745cfe741e6b00b835.png?size=240&passthrough=true",
    "label": "Three happy strawberries are hanging out together on a vine",
    "category": "decorations",
    "emoji": "<emoji_1217625936015392890:1238865168881156157>"
  },
  {
    "id": "1217626041456001146",
    "url": "https://cdn.discordapp.com/avatar-decoration-presets/a_4cd9ae5a8d103c219eacd3674d7730cd.png?size=240&passthrough=true",
    "label": "Two butterflies flutter around the avatar",
    "category": "decorations",
    "emoji": "<emoji_1217626041456001146:1238865181472456785>"
  },
  {
    "id": "1217626222851391529",
    "url": "https://cdn.discordapp.com/avatar-decoration-presets/a_ab95c78401ce4ec85c25a6d308db9d85.png?size=240&passthrough=true",
    "label": "Three merry flowerheads are quite entertained by the gentle descent of petals around them.",
    "category": "decorations",
    "emoji": "<emoji_1217626222851391529:1238865201621893241>"
  },
  {
    "id": "1212569455880699944",
    "url": "https://cdn.discordapp.com/avatar-decoration-presets/a_c3cffc19e9784f7d0b005eecdf1b566e.png?size=240&passthrough=true",
    "label": "Cat ears and whiskers adorn the avatar",
    "category": "decorations",
    "emoji": "<emoji_1212569455880699944:1238865210689716234>"
  },
  {
    "id": "1212569932391387137",
    "url": "https://cdn.discordapp.com/avatar-decoration-presets/a_f3af281c65cf0cf590e9e1f59e9c6cf6.png?size=240&passthrough=true",
    "label": "Waves of crackling energy surrounds the avatar",
    "category": "decorations",
    "emoji": "<emoji_1212569932391387137:1238865223704645642>"
  },
  {
    "id": "1212570367017885737",
    "url": "https://cdn.discordapp.com/avatar-decoration-presets/a_3e1fc3c7ee2e34e8176f4737427e8f4f.png?size=240&passthrough=true",
    "label": "Hearts and flowers decorate the avatar's frame for a lovely",
    "category": "decorations",
    "emoji": "<emoji_1212570367017885737:1238865242948374590>"
  },
  {
    "id": "1212570617404981348",
    "url": "https://cdn.discordapp.com/avatar-decoration-presets/a_51d3bb502109eec26c76386ec980bc8b.png?size=240&passthrough=true",
    "label": "A drop of sweat slides down the avatar's frame",
    "category": "decorations",
    "emoji": "<emoji_1212570617404981348:1238865254520324168>"
  },
  {
    "id": "1212581170823561236",
    "url": "https://cdn.discordapp.com/avatar-decoration-presets/a_a0db4314b8cc271c8f472357aa895005.png?size=240&passthrough=true",
    "label": "The avatar emits an exclamation mark",
    "category": "decorations",
    "emoji": "<emoji_1212581170823561236:1238865269317697618>"
  },
  {
    "id": "1212581413958979634",
    "url": "https://cdn.discordapp.com/avatar-decoration-presets/a_4cc97277177b166fd7d4af3bdb370815.png?size=240&passthrough=true",
    "label": "A sobbing avatar lets loose a cascade of tears.",
    "category": "decorations",
    "emoji": "<emoji_1212581413958979634:1238865295393947728>"
  },
  {
    "id": "1154896010255015996",
    "url": "https://cdn.discordapp.com/avatar-decoration-presets/a_c7e1751e8122f1b475cb3006966fb28c.png?size=240&passthrough=true",
    "label": "Radiating Energy Circle with Lightning",
    "category": "decorations",
    "emoji": "<emoji_1154896010255015996:1238865419545214986>"
  },
  {
    "id": "1144305233707671574",
    "url": "https://cdn.discordapp.com/avatar-decoration-presets/a_c3c09bd122898be35093d0d59850f627.png?size=240&passthrough=true",
    "label": "Wavy Ghost with Shocked Expression",
    "category": "decorations",
    "emoji": "<emoji_1144305233707671574:1238865438813851678>"
  },
  {
    "id": "1144307257807491095",
    "url": "https://cdn.discordapp.com/avatar-decoration-presets/a_55c9d0354290afa8b7fe47ea9bd7dbcf.png?size=240&passthrough=true",
    "label": "Sweat Drops with Question Mark Speech Bubble",
    "category": "decorations",
    "emoji": "<emoji_1144307257807491095:1238865446501875862>"
  },
  {
    "id": "1144307629225672847",
    "url": "https://cdn.discordapp.com/avatar-decoration-presets/a_d72066b8cecbadd9fc951913ebcc384f.png?size=240&passthrough=true",
    "label": "Twinkling Lines and Stars",
    "category": "decorations",
    "emoji": "<emoji_1144307629225672847:1238865583265546313>"
  },
  {
    "id": "1144307957425778780",
    "url": "https://cdn.discordapp.com/avatar-decoration-presets/a_8ffa2ba9bff18e96b76c2e66fd0d7fa3.png?size=240&passthrough=true",
    "label": "Speech Bubble with Lovestruck Expression and Floating Hearts",
    "category": "decorations",
    "emoji": "<emoji_1144307957425778780:1238865597899739198>"
  },
  {
    "id": "1174460891727663244",
    "url": "https://cdn.discordapp.com/avatar-decoration-presets/a_b98e8b204d59882fb7f9f7c86922c0bf.png?size=240&passthrough=true",
    "label": "Thick Exclamation Lines with Japanese Hiragana Speech Bubble",
    "category": "decorations",
    "emoji": "<emoji_1174460891727663244:1238865610658812034>"
  },
  {
    "id": "1144308439720394945",
    "url": "https://cdn.discordapp.com/avatar-decoration-presets/a_3c97a2d37f433a7913a1c7b7a735d000.png?size=240&passthrough=true",
    "label": "Anger Symbol with Exclamation Mark Speech Bubble",
    "category": "decorations",
    "emoji": "<emoji_1144308439720394945:1238865624873046118>"
  },
  {
    "id": "1207047386778697828",
    "url": "https://cdn.discordapp.com/avatar-decoration-presets/a_a065206df7b011a5510e4e5bca7d49be.png?size=240&passthrough=true",
    "label": "Three fireballs revolve around the avatar's frame",
    "category": "decorations",
    "emoji": "<emoji_1207047386778697828:1238865654187032730>"
  },
  {
    "id": "1207047673673420860",
    "url": "https://cdn.discordapp.com/avatar-decoration-presets/a_250640ab00a8837a1d56f35879138177.png?size=240&passthrough=true",
    "label": "Droplets and streaks of water dance and swirl around the avatar.",
    "category": "decorations",
    "emoji": "<emoji_1207047673673420860:1238865676815437874>"
  },
  {
    "id": "1207047813888872518",
    "url": "https://cdn.discordapp.com/avatar-decoration-presets/a_554b7c34f7b6c709f19535aacb128e7b.png?size=240&passthrough=true",
    "label": "A sphere of gusting wind swirls around the avatar.",
    "category": "decorations",
    "emoji": "<emoji_1207047813888872518:1238865702148902914>"
  },
  {
    "id": "1207048053006139492",
    "url": "https://cdn.discordapp.com/avatar-decoration-presets/a_fa014594d4b2b4249e1098c0adc85b47.png?size=240&passthrough=true",
    "label": "A large chunk of earthly rock is split into five smaller chunks.",
    "category": "decorations",
    "emoji": "<emoji_1207048053006139492:1238865724353810582>"
  },
  {
    "id": "1207048292551368745",
    "url": "https://cdn.discordapp.com/avatar-decoration-presets/a_365eed4178528fe8293c4212e8e2d5cb.png?size=240&passthrough=true",
    "label": "A streak of electricity jolts around the avatar",
    "category": "decorations",
    "emoji": "<emoji_1207048292551368745:1238865751322923059>"
  },
  {
    "id": "1207048659666079814",
    "url": "https://cdn.discordapp.com/avatar-decoration-presets/a_82e4df4028396ad5ccaaafb397fa6248.png?size=240&passthrough=true",
    "label": "Fire",
    "category": "decorations",
    "emoji": "<emoji_1207048659666079814:1238865782528806932>"
  },
  {
    "id": "1197344345783808161",
    "url": "https://cdn.discordapp.com/avatar-decoration-presets/a_e90ebc0114e7bdc30353c8b11953ea41.png?size=240&passthrough=true",
    "label": "Something disrupted the neurovisor connection. The signal appears as static over the avatar. Better call Repairs.",
    "category": "decorations",
    "emoji": "<emoji_1197344345783808161:1238865807300231270>"
  },
  {
    "id": "1197344413718949938",
    "url": "https://cdn.discordapp.com/avatar-decoration-presets/a_c6b3bc1dc49e5b284dca0b6437831004.png?size=240&passthrough=true",
    "label": "A glowing neon HUD overlays the avatar",
    "category": "decorations",
    "emoji": "<emoji_1197344413718949938:1238865847133540363>"
  },
  {
    "id": "1197344598675165204",
    "url": "https://cdn.discordapp.com/avatar-decoration-presets/a_cc83efd93ecd6e41857449c3c0ef9b22.png?size=240&passthrough=true",
    "label": "After booting up",
    "category": "decorations",
    "emoji": "<emoji_1197344598675165204:1238865871007387668>"
  },
  {
    "id": "1197344653515690054",
    "url": "https://cdn.discordapp.com/avatar-decoration-presets/a_172fa9da0af8698e37f5e5de76637439.png?size=240&passthrough=true",
    "label": "A surge of energy pulses through wires perched on top of this avatar. Electricity dangerously crackles over the image. Be careful with this one!",
    "category": "decorations",
    "emoji": "<emoji_1197344653515690054:1238865895913427049>"
  },
  {
    "id": "1144005849740742707",
    "url": "https://cdn.discordapp.com/avatar-decoration-presets/a_0f5d6c4dd8ae74662ee9c40722a56cbd.png?size=240&passthrough=true",
    "label": "Curved Sword with Pink Gem Engraved in Hilt",
    "category": "decorations",
    "emoji": "<emoji_1144005849740742707:1238865944051454053>"
  },
  {
    "id": "1144007738859470929",
    "url": "https://cdn.discordapp.com/avatar-decoration-presets/a_1dbc603c181999b9815cb426dfec71a6.png?size=240&passthrough=true",
    "label": "Round Glass Bottle with Cork",
    "category": "decorations",
    "emoji": "<emoji_1144007738859470929:1238865999781040160>"
  },
  {
    "id": "1144046002110738635",
    "url": "https://cdn.discordapp.com/avatar-decoration-presets/a_fe3c76cac2adf426832a7e495e8329d3.png?size=240&passthrough=true",
    "label": "Three Fairy Sprites",
    "category": "decorations",
    "emoji": "<emoji_1144046002110738635:1238866030823215155>"
  },
  {
    "id": "1144048390594908213",
    "url": "https://cdn.discordapp.com/avatar-decoration-presets/a_db9baf0ba7cf449d2b027c06309dbe8d.png?size=240&passthrough=true",
    "label": "Wizard's Staff with Green Gem",
    "category": "decorations",
    "emoji": "<emoji_1144048390594908213:1238866064524443688>"
  },
  {
    "id": "1144048977138946231",
    "url": "https://cdn.discordapp.com/avatar-decoration-presets/a_d650e22f6c4bab4fc0969e9d35edbcb0.png?size=240&passthrough=true",
    "label": "Circle of Blue Rune Stones",
    "category": "decorations",
    "emoji": "<emoji_1144048977138946231:1238866137945735269>"
  },
  {
    "id": "1144049316009353339",
    "url": "https://cdn.discordapp.com/avatar-decoration-presets/a_29a0533cb3de61aa8179810188f3830d.png?size=240&passthrough=true",
    "label": "Shield with Blue Gem Below a Branch of Green Leaves",
    "category": "decorations",
    "emoji": "<emoji_1144049316009353339:1238866182568935557>"
  },
  {
    "id": "1144049603109470371",
    "url": "https://cdn.discordapp.com/avatar-decoration-presets/a_9d67a1cbf81fe7197c871e94f619b04b.png?size=240&passthrough=true",
    "label": "Skull Medallion Hanging from Pink Band",
    "category": "decorations",
    "emoji": "<emoji_1144049603109470371:1238866231113810011>"
  },
  {
    "id": "1144049924397334652",
    "url": "https://cdn.discordapp.com/avatar-decoration-presets/a_4c9f2ec29c05755456dbce45d8190ed4.png?size=240&passthrough=true",
    "label": "Gold Key with Red Gem",
    "category": "decorations",
    "emoji": "<emoji_1144049924397334652:1238866283802525727>"
  },
  {
    "id": "1144058522808614924",
    "url": "https://cdn.discordapp.com/avatar-decoration-presets/a_d3da36040163ee0f9176dfe7ced45cdc.png?size=240&passthrough=true",
    "label": "Futuristic Headphones",
    "category": "decorations",
    "emoji": "<emoji_1144058522808614924:1238866295789715487>"
  },
  {
    "id": "1144058844004233370",
    "url": "https://cdn.discordapp.com/avatar-decoration-presets/a_fed43ab12698df65902ba06727e20c0e.png?size=240&passthrough=true",
    "label": "Futuristic Interface",
    "category": "decorations",
    "emoji": "<emoji_1144058844004233370:1238866301443641406>"
  },
  {
    "id": "1144059132517826602",
    "url": "https://cdn.discordapp.com/avatar-decoration-presets/a_10b9f886b513b77ccdd67c8784f1a496.png?size=240&passthrough=true",
    "label": "Smoke with Green Shining Border",
    "category": "decorations",
    "emoji": "<emoji_1144059132517826602:1238866317260488716>"
  },
  {
    "id": "Libya",
    "name": "Libya",
    "category": "flags",
    "url": "https://i.ibb.co/VJ7q2FV/ezgif-7-a2ecd1b7f9.png",
    "emoji": "<emoji_Libya:1238866345001488405>"
  },
  {
    "id": "Algeria",
    "name": "Algeria",
    "category": "flags",
    "url": "https://i.ibb.co/C7Zdqnp/ezgif-1-148d3d8ea9.png",
    "emoji": "<emoji_Algeria:1238866377457008761>"
  },
  {
    "id": "Bahrain",
    "name": "Bahrain",
    "category": "flags",
    "url": "https://i.ibb.co/Dr5gMvn/ezgif-1-bf03b81f9d.png",
    "emoji": "<emoji_Bahrain:1238866416615161896>"
  },
  {
    "id": "Comoros",
    "name": "Comoros",
    "category": "flags",
    "url": "https://i.ibb.co/9nqKx3b/ezgif-1-f0b73c7a9f.png",
    "emoji": "<emoji_Comoros:1238866462190338118>"
  },
  {
    "id": "Tunisia",
    "name": "Tunisia",
    "category": "flags",
    "url": "https://i.ibb.co/Ksqq6d7/ezgif-7-727033509f.png",
    "emoji": "<emoji_Tunisia:1238866496583630888>"
  },
  {
    "id": "UAE",
    "name": "UAE",
    "category": "flags",
    "url": "https://i.ibb.co/mSRswm8/ezgif-7-637d28d3db.png",
    "emoji": "<emoji_UAE:1238866518633218079>"
  },
  {
    "id": "Somalia",
    "name": "Somalia",
    "category": "flags",
    "url": "https://i.ibb.co/Sn84j7t/ezgif-7-0f127c7b46.png",
    "emoji": "<emoji_Somalia:1238866550161674291>"
  },
  {
    "id": "Sudan",
    "name": "Sudan",
    "category": "flags",
    "url": "https://i.ibb.co/TLTD2Jk/ezgif-7-b07f2e63fe.png",
    "emoji": "<emoji_Sudan:1238866592843038762>"
  },
  {
    "id": "Syria",
    "name": "Syria",
    "category": "flags",
    "url": "https://i.ibb.co/dQvcZQp/ezgif-7-369d86d58c.png",
    "emoji": "<emoji_Syria:1238866615580364931>"
  },
  {
    "id": "Yemen",
    "name": "Yemen",
    "category": "flags",
    "url": "https://i.ibb.co/kDF5G5v/ezgif-7-ea2030a439.png",
    "emoji": "<emoji_Yemen:1238866635826266122>"
  },
  {
    "id": "Overlay",
    "name": "Overlay",
    "category": "flags",
    "url": "https://i.ibb.co/hZD0mmM/ezgif-7-699c07f6f4.png",
    "emoji": "<emoji_Overlay:1238866653874356255>"
  },
  {
    "id": "Palestine",
    "name": "Palestine",
    "category": "flags",
    "url": "https://i.ibb.co/w6b12fc/ezgif-7-5217c6ff98.png",
    "emoji": "<emoji_Palestine:1238866730600632360>"
  },
  {
    "id": "Qatar",
    "name": "Qatar",
    "category": "flags",
    "url": "https://i.ibb.co/xs2Lktj/ezgif-7-44263314da.png",
    "emoji": "<emoji_Qatar:1238866782140502178>"
  },
  {
    "id": "Saudi",
    "name": "Saudi",
    "category": "flags",
    "url": "https://i.ibb.co/rGYFpWw/ezgif-7-8da0a9f5eb.png",
    "emoji": "<emoji_Saudi:1238866821667356843>"
  },
  {
    "id": "Jordan",
    "name": "Jordan",
    "category": "flags",
    "url": "https://i.ibb.co/hyBBCB7/ezgif-7-df80ea6e6e.png",
    "emoji": "<emoji_Jordan:1238866856173899796>"
  },
  {
    "id": "Kuwait",
    "name": "Kuwait",
    "category": "flags",
    "url": "https://i.ibb.co/y58DkH5/ezgif-7-af7e8c28ab.png",
    "emoji": "<emoji_Kuwait:1238866884825452594>"
  },
  {
    "id": "Lebanon",
    "name": "Lebanon",
    "category": "flags",
    "url": "https://i.ibb.co/LPYNzGG/ezgif-7-d9dc5b4cc6.png",
    "emoji": "<emoji_Lebanon:1238866953435746424>"
  },
  {
    "id": "Mauritania",
    "name": "Mauritania",
    "category": "flags",
    "url": "https://i.ibb.co/8mZKC19/ezgif-7-f78d395b85.png",
    "emoji": "<emoji_Mauritania:1238867038009688064>"
  },
  {
    "id": "Morocco",
    "name": "Morocco",
    "category": "flags",
    "url": "https://i.ibb.co/kSdbdCn/ezgif-7-f3b2fab832.png",
    "emoji": "<emoji_Morocco:1238867079466057840>"
  },
  {
    "id": "Djibouti",
    "name": "Djibouti",
    "category": "flags",
    "url": "https://i.ibb.co/cQFNw8G/ezgif-1-92158fd061.png",
    "emoji": "<emoji_Djibouti:1238867120553590826>"
  },
  {
    "id": "Egypt",
    "name": "Egypt",
    "category": "flags",
    "url": "https://i.ibb.co/hs9GjBp/ezgif-7-f21e193074.png",
    "emoji": "<emoji_Egypt:1238867158034022470>"
  },
  {
    "id": "iraq",
    "name": "iraq",
    "category": "flags",
    "url": "https://i.ibb.co/Q6CLZyM/ezgif-7-126237475a.png",
    "emoji": "<emoji_iraq:1238867206050152571>"
  }
]